hellomydarlin/__init__.py
hellomydarlin-0.0.24.dist-info/METADATA
hellomydarlin-0.0.24.dist-info/WHEEL
hellomydarlin-0.0.24.dist-info/top_level.txt
hellomydarlin-0.0.24.dist-info/RECORD
