Metadata-Version: 2.1
Name: hellomydarlin
Version: 0.0.24
Summary: Says Hello
Home-page: UNKNOWN
Author: Stephen Burwell
Author-email: UNKNOWN
License: UNKNOWN
Keywords: python
Platform: UNKNOWN
Classifier: Development Status :: 1 - Planning
Classifier: Intended Audience :: Developers
Classifier: Programming Language :: Python :: 3
Classifier: Operating System :: Unix
Classifier: Operating System :: MacOS :: MacOS X
Classifier: Operating System :: Microsoft :: Windows
